rpc_sdk/__init__.py
rpc_sdk/admin.py
rpc_sdk/agent.py
rpc_sdk/client.py
rpc_sdk/exceptions.py
mp_rpc_sdk-1.0.0.dist-info/METADATA
mp_rpc_sdk-1.0.0.dist-info/WHEEL
mp_rpc_sdk-1.0.0.dist-info/top_level.txt
mp_rpc_sdk-1.0.0.dist-info/RECORD
