Metadata-Version: 2.1
Name: mp-rpc-sdk
Version: 1.0.0
Summary: Python SDK for Browser RPC System
Home-page: https://github.com/example/rpc-system
Author: RPC Team
License: UNKNOWN
Platform: UNKNOWN
Classifier: Development Status :: 4 - Beta
Classifier: Intended Audience :: Developers
Classifier: License :: OSI Approved :: MIT License
Classifier: Operating System :: OS Independent
Classifier: Programming Language :: Python :: 3
Classifier: Programming Language :: Python :: 3.8
Classifier: Programming Language :: Python :: 3.9
Classifier: Programming Language :: Python :: 3.10
Classifier: Programming Language :: Python :: 3.11
Classifier: Programming Language :: Python :: 3.12
Requires-Python: >=3.8
Requires-Dist: requests (>=2.28.0)
Provides-Extra: dev
Requires-Dist: pytest-cov (>=4.0.0) ; extra == 'dev'
Requires-Dist: pytest (>=7.0.0) ; extra == 'dev'
